MANIFEST.in
README.rst
setup.py
docs/HISTORY.txt
docs/INSTALL.txt
docs/LICENSE.GPL
docs/LICENSE.txt
docs/_static/add_textblock.png
ftw/__init__.py
ftw.simplelayout.egg-info/PKG-INFO
ftw.simplelayout.egg-info/SOURCES.txt
ftw.simplelayout.egg-info/dependency_links.txt
ftw.simplelayout.egg-info/entry_points.txt
ftw.simplelayout.egg-info/namespace_packages.txt
ftw.simplelayout.egg-info/not-zip-safe
ftw.simplelayout.egg-info/requires.txt
ftw.simplelayout.egg-info/top_level.txt
ftw/simplelayout/__init__.py
ftw/simplelayout/behaviors.zcml
ftw/simplelayout/configuration.py
ftw/simplelayout/configure.zcml
ftw/simplelayout/handlers.py
ftw/simplelayout/indexer.py
ftw/simplelayout/interfaces.py
ftw/simplelayout/lawgiver.zcml
ftw/simplelayout/migration.py
ftw/simplelayout/permissions.zcml
ftw/simplelayout/properties.py
ftw/simplelayout/resources.zcml
ftw/simplelayout/testing.py
ftw/simplelayout/trash.py
ftw/simplelayout/utils.py
ftw/simplelayout/aliasblock/__init__.py
ftw/simplelayout/aliasblock/configure.zcml
ftw/simplelayout/aliasblock/hooks.py
ftw/simplelayout/aliasblock/lawgiver.zcml
ftw/simplelayout/aliasblock/permissions.zcml
ftw/simplelayout/aliasblock/resources.zcml
ftw/simplelayout/aliasblock/Extensions/install.py
ftw/simplelayout/aliasblock/browser/__init__.py
ftw/simplelayout/aliasblock/browser/aliasblock.py
ftw/simplelayout/aliasblock/browser/configure.zcml
ftw/simplelayout/aliasblock/browser/viewlet.py
ftw/simplelayout/aliasblock/browser/resources/aliasblock.scss
ftw/simplelayout/aliasblock/browser/templates/aliasblock.pt
ftw/simplelayout/aliasblock/browser/templates/aliasblock_form_viewlet.pt
ftw/simplelayout/aliasblock/contents/__init__.py
ftw/simplelayout/aliasblock/contents/aliasblock.py
ftw/simplelayout/aliasblock/contents/configure.zcml
ftw/simplelayout/aliasblock/contents/interfaces.py
ftw/simplelayout/aliasblock/profiles/default/metadata.xml
ftw/simplelayout/aliasblock/profiles/default/propertiestool.xml
ftw/simplelayout/aliasblock/profiles/default/rolemap.xml
ftw/simplelayout/aliasblock/profiles/default/types.xml
ftw/simplelayout/aliasblock/profiles/default/workflows.xml
ftw/simplelayout/aliasblock/profiles/default/types/Plone_Site.xml
ftw/simplelayout/aliasblock/profiles/default/types/ftw.simplelayout.AliasBlock.xml
