Metadata-Version: 2.1
Name: ftw.simplelayout
Version: 3.0.3
Summary: SimpleLayout provides block based content pages
Home-page: https://github.com/4teamwork/ftw.simplelayout
Author: 4teamwork AG
Author-email: mailto:info@4teamwork.ch
Maintainer: Mathias Leimgruber
License: GPL2
Keywords: ftw plone simplelayout block contentpage
Platform: UNKNOWN
Classifier: Framework :: Plone
Classifier: Framework :: Plone :: 4.3
Classifier: Framework :: Plone :: 5.1
Classifier: License :: OSI Approved :: GNU General Public License (GPL)
Classifier: Programming Language :: Python
Classifier: Programming Language :: Python :: 2.7
Classifier: Topic :: Software Development :: Libraries :: Python Modules
Provides-Extra: tests
Provides-Extra: test
Provides-Extra: contenttypes
Provides-Extra: mapblock
Provides-Extra: plone4
Provides-Extra: trash
Provides-Extra: restapi
